[{"user_id":1,"first_name":"Tracie","last_name":"Rawsen","email":"trawsen0@networksolutions.com","age":37,"gender":"Gender Questioning","job_title":"Software Consultant","phone_number":"309-588-6491"},
{"user_id":2,"first_name":"Zeke","last_name":"Novacek","email":"znovacek1@cargocollective.com","age":23,"gender":"Cisgender Man","job_title":"Speech Pathologist","phone_number":"520-540-5519"},
{"user_id":3,"first_name":"Chiquita","last_name":"Gyurkovics","email":"cgyurkovics2@amazon.com","age":67,"gender":"Non-binary","job_title":"Quality Engineer","phone_number":"828-557-7431"},
{"user_id":4,"first_name":"Rebeca","last_name":"Mandal","email":"rmandal3@github.com","age":73,"gender":"Pangender","job_title":"Environmental Specialist","phone_number":"607-948-4089"},
{"user_id":5,"first_name":"Benedikt","last_name":"Northway","email":"bnorthway4@springer.com","age":45,"gender":"Gender Nonconforming","job_title":"Database Administrator I","phone_number":"910-621-6800"},
{"user_id":6,"first_name":"Edd","last_name":"Stubley","email":"estubley5@berkeley.edu","age":69,"gender":"Trans Female","job_title":"Human Resources Manager","phone_number":"450-982-0353"},
{"user_id":7,"first_name":"Claudelle","last_name":"Penton","email":"cpenton6@sakura.ne.jp","age":56,"gender":"Gender Variant","job_title":"Financial Analyst","phone_number":"903-608-4224"},
{"user_id":8,"first_name":"Hasheem","last_name":"McDermot","email":"hmcdermot7@cisco.com","age":30,"gender":"Cis Man","job_title":"Project Manager","phone_number":"192-884-4534"},
{"user_id":9,"first_name":"Carlin","last_name":"Szymanski","email":"cszymanski8@craigslist.org","age":72,"gender":"Neither","job_title":"Legal Assistant","phone_number":"841-282-0105"},
{"user_id":10,"first_name":"Gregor","last_name":"Stapells","email":"gstapells9@etsy.com","age":18,"gender":"Trans Woman","job_title":"Automation Specialist II","phone_number":"218-576-1064"},
{"user_id":11,"first_name":"Leta","last_name":"Tyrone","email":"ltyronea@fda.gov","age":31,"gender":"Cisgender","job_title":"Cost Accountant","phone_number":"528-421-1214"},
{"user_id":12,"first_name":"Valentina","last_name":"Kewzick","email":"vkewzickb@taobao.com","age":41,"gender":"Transgender","job_title":"Registered Nurse","phone_number":"887-893-4323"},
{"user_id":13,"first_name":"Shalom","last_name":"McTurk","email":"smcturkc@chron.com","age":79,"gender":"Gender Nonconforming","job_title":"Technical Writer","phone_number":"785-159-1389"},
{"user_id":14,"first_name":"Patin","last_name":"Assad","email":"passadd@sina.com.cn","age":74,"gender":"Neither","job_title":"Graphic Designer","phone_number":"651-295-8092"},
{"user_id":15,"first_name":"Mamie","last_name":"Beau","email":"mbeaue@topsy.com","age":67,"gender":"Pangender","job_title":"Clinical Specialist","phone_number":"758-102-8782"}]